AUTHORS
COPYING
LICENSE
MANIFEST.in
RELEASE-NOTES
setup.py
test.py
examples/common.py
examples/creating_sets.py
examples/set_operations.py
examples/visualizations.py
fuzz/__init__.py
fuzz/fgraph.py
fuzz/fnumber.py
fuzz/fset.py
fuzz/graph.py
fuzz/iset.py
fuzz/visualization.py
fuzz/visplugins/__init__.py
fuzz/visplugins/abc_plugin.py
fuzz/visplugins/graph_pydot.py
fuzz/visplugins/num_gnuplot.py
fuzzpy.egg-info/PKG-INFO
fuzzpy.egg-info/SOURCES.txt
fuzzpy.egg-info/dependency_links.txt
fuzzpy.egg-info/top_level.txt