Metadata-Version: 1.0
Name: fuzzpy
Version: 0.4.2
Summary: Library for fuzzy sets, fuzzy graphs, and general fuzzy mathematics for Python.
Home-page: http://github.com/ezod/fuzzpy
Author: Aaron Mavrinac
Author-email: mavrin1@uwindsor.ca
License: LGPL
Download-URL: http://github.com/downloads/ezod/fuzzpy/fuzzpy-0.4.2.tar.bz2
Keywords: fuzzy set graph math
Platform: UNKNOWN
